openneuro_firstlevel/__init__.py
openneuro_firstlevel/dataset_designs.py
openneuro_firstlevel/diagnostics.py
openneuro_firstlevel/first_level.py
openneuro_firstlevel/second_level.py
openneuro_firstlevel/utils.py
openneurofirstlevel-0.2.dist-info/METADATA
openneurofirstlevel-0.2.dist-info/WHEEL
openneurofirstlevel-0.2.dist-info/top_level.txt
openneurofirstlevel-0.2.dist-info/RECORD
